apispec_pydantic_plugin/__init__.py
apispec_pydantic_plugin/constants.py
apispec_pydantic_plugin/errors.py
apispec_pydantic_plugin/models.py
apispec_pydantic_plugin/py.typed
apispec_pydantic_plugin/pydantic_plugin.py
apispec_pydantic_plugin/registry.py
apispec_pydantic_plugin/resolver.py
apispec_pydantic_plugin-0.7.0.dist-info/METADATA
apispec_pydantic_plugin-0.7.0.dist-info/WHEEL
apispec_pydantic_plugin-0.7.0.dist-info/RECORD
