Metadata-Version: 2.4
Name: apispec-pydantic-plugin
Version: 0.7.0
Summary: A plugin to enable support for Pydantic models in APISpec.
Project-URL: repository, https://github.com/kkirsche/apispec-pydantic-plugin
Author-email: Kevin Kirsche <kevin.kirsche@one.verizon.com>
Requires-Python: >=3.10
Requires-Dist: apispec>=6.6.1
Requires-Dist: pydantic>=2.8.2
